[
 {
  "date": "2026-07-13",
  "nq_price": 7545.3198,
  "call_wall": 7575.0,
  "put_wall": 7495.0,
  "gamma_flip": 7525.2,
  "em_high": 7563.1,
  "em_low": 7527.5,
  "net_gex_bn": 16.49,
  "basis": 0.0
 },
 {
  "date": "2026-07-14",
  "nq_price": 7534.7402,
  "call_wall": 7575.0,
  "put_wall": 7505.0,
  "gamma_flip": 7526.7,
  "em_high": 7561.8,
  "em_low": 7507.7,
  "net_gex_bn": 11.62,
  "basis": 0.0
 },
 {
  "date": "2026-07-15",
  "nq_price": 7543.5898,
  "call_wall": 7600.0,
  "put_wall": 7300.0,
  "gamma_flip": 7535.1,
  "em_high": 7575.4,
  "em_low": 7511.7,
  "net_gex_bn": 27.21,
  "basis": 0.0
 },
 {
  "date": "2026-07-16",
  "nq_price": 7510.23,
  "call_wall": 7600.0,
  "put_wall": 7515.0,
  "gamma_flip": 7540.8,
  "em_high": 7607.4,
  "em_low": 7510.2,
  "net_gex_bn": -52.24,
  "basis": 0.0
 },
 {
  "date": "2026-07-17",
  "nq_price": 7533.77,
  "call_wall": 7600.0,
  "put_wall": 7515.0,
  "gamma_flip": 7552.8,
  "em_high": 7620.4,
  "em_low": 7497.2,
  "net_gex_bn": -62.21,
  "basis": 0.0
 },
 {
  "date": "2026-07-20",
  "nq_price": 7457.6899,
  "call_wall": 7600.0,
  "put_wall": 7300.0,
  "gamma_flip": 7483.2,
  "em_high": 7520.4,
  "em_low": 7374.6,
  "net_gex_bn": -14.27,
  "basis": 0.0
 },
 {
  "date": "2026-07-21",
  "nq_price": 7443.2798,
  "call_wall": 7600.0,
  "put_wall": 7300.0,
  "gamma_flip": 7476.6,
  "em_high": 7557.8,
  "em_low": 7420.5,
  "net_gex_bn": -17.9,
  "basis": 0.0
 },
 {
  "date": "2026-07-22",
  "nq_price": 7509.2002,
  "call_wall": 7600.0,
  "put_wall": 7300.0,
  "gamma_flip": 7510.0,
  "em_high": 7547.8,
  "em_low": 7432.1,
  "net_gex_bn": -14.74,
  "basis": 0.0
 },
 {
  "date": "2026-07-24",
  "nq_price": 7408.2998,
  "call_wall": 7600.0,
  "put_wall": 7300.0,
  "gamma_flip": 7462.6,
  "em_high": 7482.5,
  "em_low": 7354.0,
  "net_gex_bn": -37.91,
  "basis": 0.0
 }
]